Workbook

Sheet Cap table
A1: ADMINISTRATIVO - pro-forma cap table (fully diluted, notional units)
A2: Today = founders' statement (SRL, 51/49, no investors, no options). Pre-seed = this round. Seed = ILLUSTRATIVE only (not a plan, not a commitment). Units are notional (10,000 = 100% today); the SRL's real social parts are [TO CONFIRM].
A4: Input | B4: Value | J4: Note
A5: Founders' units today (notional) | B5: 10000 | J5: notional
A6: Miroslav Maletici share today | B6: 0.51 | J6: founders' statement
A7: Răzvan Pervulescu share today | B7: 0.49 | J7: founders' statement
A8: Pre-seed: Vest Ventures accelerator ticket (EUR) | B8: 135000 | J8: Vest Ventures Accelerator: EUR 10k-200k (vestventures.vc)
A9: Pre-seed: independent angels (EUR) | B9: 15000 | J9: >= 10% private co-investment rule
A10: Pre-seed: pre-money valuation, fully diluted (EUR) | B10: 1250000 | J10: same as financial-model.xlsx
A11: Pre-seed: ESOP pool, % post-money, created pre-money | B11: 0.1 | J11: dilutes founders only
A12: Seed (ILLUSTRATIVE): amount (EUR) | B12: 1000000 | J12: VV Seed range EUR 200k-1M; RO avg seed 2025 EUR 1.5M (How to Web & Underline Ventures)
A13: Seed (ILLUSTRATIVE): pre-money valuation (EUR) | B13: 4000000 | J13: ILLUSTRATIVE assumption, needs traction
A14: Seed (ILLUSTRATIVE): ESOP top-up, % post-seed | B14: 0 | J14: 0 = no top-up
A16: Derived
A17: Pre-seed round (EUR) | B17: =B8+B9 -> 150000
A18: Pre-seed post-money (EUR) | B18: =B10+B17 -> 1400000
A19: Pre-seed investors' % post | B19: =B17/B18 -> 0.10714286
A20: Pre-seed FD units post | B20: =B5/(1-B19-B11) -> 12612.613
A21: Pre-seed price per unit (EUR) | B21: =B10/(B5+B11*B20) -> 111
A22: Seed post-money (EUR) | B22: =B13+B12 -> 5000000
A23: Seed investors' % post | B23: =B12/B22 -> 0.2
A24: Seed FD units post | B24: =B20/(1-B23-B14) -> 15765.766
A25: Seed price per unit (EUR) | B25: =B13/(B20+B14*B24) -> 317.14286
A28: Holder | B28: Today units | C28: Today % | D28: Pre-seed units | E28: Pre-seed % | F28: Seed units | G28: Seed % | H28: Invested (EUR)
A29: Miroslav Maletici (co-founder) | B29: =B5*B6 -> 5100 | C29: =B29/$B$35 -> 0.51 | D29: =B29 -> 5100 | E29: =D29/$D$35 -> 0.40435714 | F29: =D29 -> 5100 | G29: =F29/$F$35 -> 0.32348571 | H29: 0
A30: Răzvan Pervulescu (co-founder) | B30: =B5*B7 -> 4900 | C30: =B30/$B$35 -> 0.49 | D30: =B30 -> 4900 | E30: =D30/$D$35 -> 0.3885 | F30: =D30 -> 4900 | G30: =F30/$F$35 -> 0.3108 | H30: 0
A31: ESOP pool | B31: 0 | C31: =B31/$B$35 -> 0 | D31: =B11*B20 -> 1261.2613 | E31: =D31/$D$35 -> 0.1 | F31: =D31+B14*B24 -> 1261.2613 | G31: =F31/$F$35 -> 0.08 | H31: 0
A32: Vest Ventures | B32: 0 | C32: =B32/$B$35 -> 0 | D32: =B8/B21 -> 1216.2162 | E32: =D32/$D$35 -> 0.096428571 | F32: =D32 -> 1216.2162 | G32: =F32/$F$35 -> 0.077142857 | H32: =B8 -> 135000
A33: Independent angels | B33: 0 | C33: =B33/$B$35 -> 0 | D33: =B9/B21 -> 135.13514 | E33: =D33/$D$35 -> 0.010714286 | F33: =D33 -> 135.13514 | G33: =F33/$F$35 -> 0.0085714286 | H33: =B9 -> 15000
A34: Seed investors (ILLUSTRATIVE) | B34: 0 | C34: =B34/$B$35 -> 0 | D34: 0 | E34: =D34/$D$35 -> 0 | F34: =B12/B25 -> 3153.1532 | G34: =F34/$F$35 -> 0.2 | H34: =B12 -> 1000000
A35: Total | B35: =SUM(B29:B34) -> 10000 | C35: =SUM(C29:C34) -> 1 | D35: =SUM(D29:D34) -> 12612.613 | E35: =SUM(E29:E34) -> 1 | F35: =SUM(F29:F34) -> 15765.766 | G35: =SUM(G29:G34) -> 1 | H35: =SUM(H29:H34) -> 1150000
A36: Founders combined | C36: =C29+C30 -> 1 | E36: =E29+E30 -> 0.79285714 | G36: =G29+G30 -> 0.63428571
A37: Check: units x price = post-money (pre-seed, seed) | D37: =D35*B21 -> 1400000 | F37: =F35*B25 -> 5000000

Sheet CLA alternative
A1: Alternative: convertible loan agreement (CLA) instead of priced equity
A2: Vest Ventures contracts: term sheet, then a CLA or an SHA on the fund's templates (vestventures.vc/en/programs-terms). Interest, discount and cap below are ILLUSTRATIVE inputs, not VV terms [TO CONFIRM].
A4: CLA principal (EUR) | B4: ='Cap table'!B17 -> 150000 | C4: same money as the pre-seed round
A5: Valuation cap, pre-money FD (EUR) | B5: ='Cap table'!B10 -> 1250000 | C5: cap = pre-money of the priced alternative
A6: Discount to the next priced round | B6: 0.2 | C6: ILLUSTRATIVE
A7: Annual interest (simple) | B7: 0 | C7: ILLUSTRATIVE; VV template terms [TO CONFIRM]
A8: Years until conversion | B8: 2 | C8: ILLUSTRATIVE (seed ~24 months after close: 100-customer trigger + raise)
A9: Amount converting (EUR) | B9: =B4*(1+B7*B8) -> 150000
A10: Pre-conversion units (founders + ESOP pool, notional) | B10: ='Cap table'!B5+'Cap table'!D31 -> 11261.261 | C10: same pool units as the priced round (10% of post-money), so the two paths are comparable
A11: Cap price per unit (EUR) | B11: =B5/B10 -> 111 | C11: cap / pre-conversion units
A12: Seed price per unit if no CLA (seed pre-money / pre-conversion units) | B12: ='Cap table'!B13/B10 -> 355.2 | C12: ILLUSTRATIVE seed
A13: Discounted seed price | B13: =B12*(1-B6) -> 284.16
A14: Conversion price = MIN(cap price, discounted price) | B14: =MIN(B11,B13) -> 111
A15: CLA units at conversion | B15: =B9/B14 -> 1351.3514
A16: CLA holders' % right after conversion (before seed money) | B16: =B15/(B10+B15) -> 0.10714286
A17: Seed amount (EUR) | B17: ='Cap table'!B12 -> 1000000
A18: Seed new units (at seed price, after conversion) | B18: =B17/('Cap table'!B13/(B10+B15)) -> 3153.1532 | C18: pre-money includes converted units (simplification)
A19: Total units post-seed | B19: =B10+B15+B18 -> 15765.766
A20: Founders combined after seed - CLA path | B20: =('Cap table'!B5)/B19 -> 0.63428571
A21: Founders combined after seed - priced pre-seed path | B21: ='Cap table'!G36 -> 0.63428571 | C21: from sheet 'Cap table'
A22: CLA holders after seed | B22: =B15/B19 -> 0.085714286

Sheet Notes
A1: Ownership today: Miroslav Maletici 51%, Răzvan Pervulescu 49% - founders' statement; no investors, no options issued.
A2: Legal entity named on administrativo.ro as its operator: WISELEARNING S.R.L. (CUI 50321210, J35/2618/2024) - [TO CONFIRM] that this SRL holds the 51/49 cap table.
A3: Pre-seed modelled as priced equity at EUR 1.25M pre-money, fully diluted including a new 10% ESOP pool created pre-money.
A4: Vest Ventures may use a CLA (convertible loan) or an SHA; see 'CLA alternative'.
A5: SRL governance: amendments to the articles need unanimity of associates; an SRL -> SA or holding conversion at the round is [TO CONFIRM] with a lawyer.
A6: Seed column is ILLUSTRATIVE only: no seed investor, amount or valuation has been discussed.
A7: Same figures as financial-model.xlsx, sheet 'Cap table'.
